LICENSE
MANIFEST.in
README.rst
setup.py
bin/logfollowctl.py
bin/logfollowd.py
logfollow/__init__.py
logfollow/install.py
logfollow/protocol.py
logfollow/server.py
logfollow/ui.py
logfollow_server.egg-info/PKG-INFO
logfollow_server.egg-info/SOURCES.txt
logfollow_server.egg-info/dependency_links.txt
logfollow_server.egg-info/entry_points.txt
logfollow_server.egg-info/requires.txt
logfollow_server.egg-info/top_level.txt
templates/console.html
templates/console.html~
templates/favicon.ico
templates/css/app.css
templates/images/.gitkeep
templates/js/app.js
templates/js/app.js~