Metadata-Version: 1.0
Name: logfollow-server
Version: 0.0.9
Summary: Real-time Web Monitor for your logs
Home-page: https://github.com/kachayev/logfollow
Author: Alexey S. Kachayev
Author-email: kachayev@gmail.com
License: Copyright (c) 2011, Alexey S. Kachayev, kachayev@gmail.com
